Memory/memory_512x16.v
module memory_512x16 #(
    parameter AW = 9,          // address width (512 = 2^9)
    parameter DW = 16,         // data width
    parameter INIT_FILE = ""   // optional: mem init (hex/binary)
)(
    input              clk,
    input              rst_b,
    input              we,         // write enable (active high)
    input  [AW-1:0]    addr,       // address
    input  [DW-1:0]    din,        // data in
    output reg [DW-1:0] dout       // data out
);

    reg [DW-1:0] mem [0:(1<<AW)-1];

    // Optional initialization
    integer i;
    initial begin
        if (INIT_FILE != "") 
        begin
            $readmemh(INIT_FILE, mem);
        end 
        else 
        begin
            for (i = 0; i < (1<<AW); i = i + 1)
                mem[i] = {DW{1'b0}};
        end
    end

    // Synchronous read & write (read-after-write same cycle gives new data)
    always @(posedge clk or negedge rst_b) 
    begin
        if (!rst_b) 
        begin
            dout <= {DW{1'b0}};
        end 
        else begin
            if (we)
                mem[addr] <= din;
            dout <= mem[addr];
        end
    end
endmodule

Memory/memory_512x16_tb.v
`timescale 1ns/1ps
`include "memory_512x16.v"

module memory_512x16_tb;
    reg clk;
    reg rst_b;
    reg we;
    reg [8:0] addr;
    reg [15:0] din;
    wire [15:0] dout;

    // Instanțierea modulului de memorie
    memory_512x16 #(
        .AW(9),
        .DW(16),
        .INIT_FILE("")  // fără fișier de inițializare pentru test
    ) mem (
        .clk(clk),
        .rst_b(rst_b),
        .we(we),
        .addr(addr),
        .din(din),
        .dout(dout)
    );

    // Generare clock
    initial begin
        clk = 0;
        forever #50 clk = ~clk;  // perioadă 50ns
    end

    // Test scenario
    initial begin
        $dumpfile("dump.vcd");
        $dumpvars(0, memory_512x16_tb);
        
        // Inițializare
        rst_b = 0;
        we = 0;
        addr = 9'd0;
        din = 16'd0;
        
        // Reset
        #50;
        rst_b = 1;
        #50;
        
        // Test 1: Scriere la adresa 0
        $display("Test 1: Scriere 0xABCD la adresa 0");
        we = 1;
        addr = 9'd0;
        din = 16'hABCD;
        #50;
        
        // Test 2: Citire de la adresa 0
        $display("Test 2: Citire de la adresa 0");
        we = 0;
        addr = 9'd0;
        #50;
        $display("Citit: 0x%h (așteptat: 0xABCD)", dout);
        
        // Test 3: Scriere secvențială
        $display("Test 3: Scriere secvențială la 10 adrese");
        we = 1;
        repeat(10) begin
            din = {7'b0, addr};  // valoarea = adresa
            #50;
            addr = addr + 1;
        end
        
        // Test 4: Citire secvențială
        $display("Test 4: Citire secvențială din 10 adrese");
        we = 0;
        addr = 9'd0;
        repeat(10) begin
            #50;
            $display("Adresa %d: citit 0x%h", addr, dout);
            addr = addr + 1;
        end
        
        // Test 5: Scriere la adresa maximă (511)
        $display("Test 5: Scriere 0x1234 la adresa 511");
        we = 1;
        addr = 9'd511;
        din = 16'h1234;
        #50;
        
        // Test 6: Citire de la adresa maximă
        $display("Test 6: Citire de la adresa 511");
        we = 0;
        #50;
        $display("Citit: 0x%h (așteptat: 0x1234)", dout);
        
        // Test 7: Write enable = 0 (nu scrie)
        $display("Test 7: Încercare scriere cu we=0");
        we = 0;
        addr = 9'd100;
        din = 16'hFFFF;
        #50;
        we = 0;
        #50;
        $display("Citit: 0x%h (nu ar trebui să fie 0xFFFF)", dout);
        
        // Test 8: Reset în timpul operării
        $display("Test 8: Reset în timpul operării");
        we = 1;
        addr = 9'd50;
        din = 16'hDEAD;
        #25;
        rst_b = 0;
        #50;
        rst_b = 1;
        we = 0;
        #50;
        $display("Citit după reset: 0x%h (așteptat: 0x0000)", dout);
        
        #100;
        $display("Test finalizat!");
        $finish;
    end

    // Monitor pentru debug
    initial begin
        $monitor("Time=%0t | rst_b=%b we=%b addr=%d din=0x%h dout=0x%h", 
                 $time, rst_b, we, addr, din, dout);
    end

endmodule

Memory/dump.vcd
$date
	Sat Nov  8 14:43:33 2025
$end
$version
	Icarus Verilog
$end
$timescale
	1ps
$end
$scope module memory_512x16_tb $end
$var wire 16 ! dout [15:0] $end
$var reg 9 " addr [8:0] $end
$var reg 1 # clk $end
$var reg 16 $ din [15:0] $end
$var reg 1 % rst_b $end
$var reg 1 & we $end
$scope module mem $end
$var wire 9 ' addr [8:0] $end
$var wire 1 # clk $end
$var wire 16 ( din [15:0] $end
$var wire 1 % rst_b $end
$var wire 1 & we $end
$var parameter 32 ) AW $end
$var parameter 32 * DW $end
$var parameter 0 + INIT_FILE $end
$var reg 16 , dout [15:0] $end
$var integer 32 - i [31:0] $end
$upscope $end
$upscope $end
$enddefinitions $end
$comment Show the parameter values. $end
$dumpall
b +
b10000 *
b1001 )
$end
#0
$dumpvars
b1000000000 -
b0 ,
b0 (
b0 '
0&
0%
b0 $
0#
b0 "
b0 !
$end
#50000
1%
1#
#100000
b1010101111001101 $
b1010101111001101 (
1&
0#
#150000
0&
1#
#200000
b0 $
b0 (
1&
0#
#250000
b1 $
b1 (
b1 "
b1 '
1#
#300000
b10 $
b10 (
b10 "
b10 '
0#
#350000
b11 $
b11 (
b11 "
b11 '
1#
#400000
b100 $
b100 (
b100 "
b100 '
0#
#450000
b101 $
b101 (
b101 "
b101 '
1#
#500000
b110 $
b110 (
b110 "
b110 '
0#
#550000
b111 $
b111 (
b111 "
b111 '
1#
#600000
b1000 $
b1000 (
b1000 "
b1000 '
0#
#650000
b1001 $
b1001 (
b1001 "
b1001 '
1#
#700000
0&
b0 "
b0 '
0#
#750000
b1 !
b1 ,
b1 "
b1 '
1#
#800000
b10 "
b10 '
0#
#850000
b11 !
b11 ,
b11 "
b11 '
1#
#900000
b100 "
b100 '
0#
#950000
b101 !
b101 ,
b101 "
b101 '
1#
#1000000
b110 "
b110 '
0#
#1050000
b111 !
b111 ,
b111 "
b111 '
1#
#1100000
b1000 "
b1000 '
0#
#1150000
b1001 !
b1001 ,
b1001 "
b1001 '
1#
#1200000
b1001000110100 $
b1001000110100 (
1&
b111111111 "
b111111111 '
0#
#1250000
b0 !
b0 ,
0&
1#
#1300000
b1111111111111111 $
b1111111111111111 (
b1100100 "
b1100100 '
0#
#1350000
1#
#1400000
b1101111010101101 $
b1101111010101101 (
b110010 "
b110010 '
1&
0#
#1425000
0%
#1450000
1#
#1475000
0&
1%
